.gitignore
README
distribute_setup.py
gen-bootstrap.py
setup.cfg
setup.py
docs/Makefile
docs/source/README.rst
docs/source/conf.py
docs/source/index.rst
docs/source/module.rst
ohsnap/__init__.py
ohsnap/app.py
ohsnap/archive.py
ohsnap/ext.py
ohsnap/main.py
ohsnap.egg-info/PKG-INFO
ohsnap.egg-info/SOURCES.txt
ohsnap.egg-info/dependency_links.txt
ohsnap.egg-info/entry_points.txt
ohsnap.egg-info/requires.txt
ohsnap.egg-info/top_level.txt