Metadata-Version: 1.0
Name: ohsnap
Version: 0.1.0a-20120508
Summary: A tarsnap backup manager
Home-page: http://packages.python.org/ohsnap
Author: Shawn Siefkas
Author-email: shawn@siefk.as
License: BSD
Keywords: backup tarsnap
Platform: UNKNOWN
Classifier: Development Status :: 3 - Alpha
Classifier: Topic :: Utilities
Classifier: License :: OSI Approved :: BSD License
